DESCRIPTION.rst
LICENSE
MANIFEST.in
README.md
setup.py
bashtools/__init__.py
bashtools/_version.py
bashtools/about.py
bashtools/bash_init.py
bashtools/cli.py
bashtools/colors.py
bashtools/help_menu.py
bashtools/logd.py
bashtools/oscodes_unix.py
bashtools/script_utils.py
bashtools/statics.py