Metadata-Version: 1.2
Name: bashtools
Version: 0.1.9
Summary: Bash Tools for Amazon Web Services
Home-page: https://github.com/fstab50/bashtools
Author: Blake Huber
Author-email: blakeca00@gmail.com
License: MIT
Keywords: bash Amazon Web Services AWS tools s3 ec2 lambda
Platform: UNKNOWN
Classifier: Topic :: System :: Shells
Classifier: Topic :: System :: Systems Administration
Classifier: Topic :: Utilities
Classifier: Development Status :: 4 - Beta
Classifier: Programming Language :: Python :: 3.4
Classifier: Programming Language :: Python :: 3.5
Classifier: Programming Language :: Python :: 3.6
Classifier: License :: OSI Approved :: MIT License
Classifier: Operating System :: POSIX :: Linux
Requires-Python: >=3.4, <4
